{
"type": "FeatureCollection",
"name": "airport_distance",
"crs": { "type": "name", "properties": { "name": "urn:ogc:def:crs:OGC:1.3:CRS84" } },
"features": [
{ "type": "Feature", "properties": { "name": "Columbia Regional Airport", "HubName": "Bonne Terre Estate", "HubDist": 4.0871566307922835 }, "geometry": { "type": "Point", "coordinates": [ -92.2198931, 38.8168307 ] } },
{ "type": "Feature", "properties": { "name": "St. Louis Metro-East Airport", "HubName": "Bonne Terre Estate", "HubDist": 132.6787360134858 }, "geometry": { "type": "Point", "coordinates": [ -89.8078731, 38.7342143 ] } }
]
}
